BrownBat-0.0b2.dist-info/WHEEL
BrownBat-0.0b2.dist-info/metadata.json
BrownBat-0.0b2.dist-info/top_level.txt
BrownBat-0.0b2.dist-info/DESCRIPTION.rst
BrownBat-0.0b2.dist-info/RECORD
BrownBat-0.0b2.dist-info/METADATA
brownbat/__init__.py
brownbat/core.py
brownbat/C.py
