Metadata-Version: 2.0
Name: BrownBat
Version: 0.0b2
Summary: A lazy source code generation library
Home-page: https://github.com/DouglasRaillard/BrownBat
Author: Douglas RAILLARD
Author-email: douglas.raillard.github@gmail.com
License: GNU Lesser General Public License v3 or later (LGPLv3+)
Keywords: source generation lazy code meta
Platform: UNKNOWN
Classifier: Operating System :: OS Independent
Classifier: Development Status :: 4 - Beta
Classifier: Intended Audience :: Developers
Classifier: License :: OSI Approved :: GNU Lesser General Public License v3 or later (LGPLv3+)
Classifier: Programming Language :: Python :: 3 :: Only
Classifier: Topic :: Software Development :: Code Generators
